model_track/__init__.py
model_track/binning/__init__.py
model_track/binning/bins_applier.py
model_track/binning/quantile_binner.py
model_track/binning/tree_binner.py
model_track/stability/__init__.py
model_track/stability/woe.py
model_track/stats/__init__.py
model_track/stats/categorical_correlation.py
model_track/stats/summary.py
model_track/woe/__init__.py
model_track/woe/woe_by_period.py
model_track/woe/woe_calculator.py
model_track_cr-0.2.2.dist-info/METADATA
model_track_cr-0.2.2.dist-info/WHEEL
model_track_cr-0.2.2.dist-info/RECORD
