Metadata-Version: 2.4
Name: model-track-cr
Version: 0.2.2
Summary: 
Author: Cristiano
Author-email: cristiano2132.ufv@gmail.com
Requires-Python: >=3.10,<4.0
Classifier: Programming Language :: Python :: 3
Classifier: Programming Language :: Python :: 3.10
Classifier: Programming Language :: Python :: 3.11
Classifier: Programming Language :: Python :: 3.12
Classifier: Programming Language :: Python :: 3.13
Classifier: Programming Language :: Python :: 3.14
Requires-Dist: matplotlib (>=3.7,<4.0)
Requires-Dist: numpy (>=1.23,<2.0)
Requires-Dist: pandas (>=1.5,<3.0)
Requires-Dist: scikit-learn (>=1.2,<2.0)
Requires-Dist: seaborn (>=0.12,<0.14)
